wordtodigits/__init__.py
wordtodigits-1.0.2.dist-info/METADATA
wordtodigits-1.0.2.dist-info/WHEEL
wordtodigits-1.0.2.dist-info/top_level.txt
wordtodigits-1.0.2.dist-info/RECORD
