Metadata-Version: 2.1
Name: wordtodigits
Version: 1.0.2
Summary: To convert numbers in word form to digits
Home-page: https://github.com/abhishek-rawat18/wordtodigits
Author: Abhishek Rawat
Author-email: abhishek18.official@gmail.com
License: UNKNOWN
Platform: UNKNOWN
Classifier: Programming Language :: Python :: 3
Classifier: License :: OSI Approved :: MIT License
Classifier: Operating System :: OS Independent
Requires-Python: >=3.6
